play/__init__.py
play/blank_image.png
play/color.py
play/exceptions.py
play/keypress.py
play/play.py
replit_play-0.0.23.dist-info/METADATA
replit_play-0.0.23.dist-info/WHEEL
replit_play-0.0.23.dist-info/top_level.txt
replit_play-0.0.23.dist-info/RECORD
